wormulon/__init__.py
wormulon/job.py
wormulon/jobspec.py
wormulon/session.py
wormulon/slurm.py
wormulon-0.0.1.dist-info/METADATA
wormulon-0.0.1.dist-info/WHEEL
wormulon-0.0.1.dist-info/RECORD
