Metadata-Version: 2.1
Name: wormulon
Version: 0.0.1
Summary: 
Requires-Python: >=3.10,<4.0
Classifier: Programming Language :: Python :: 3
Classifier: Programming Language :: Python :: 3.10
Classifier: Programming Language :: Python :: 3.11
Requires-Dist: paramiko (>=2.11.0,<3.0.0)
